logicalinduction/__init__.py
logicalinduction/credence.py
logicalinduction/enumerator.py
logicalinduction/enumerator_test.py
logicalinduction/formula.py
logicalinduction/inductor.py
logicalinduction/inductor_test.py
logicalinduction/sentence.py
logicalinduction/sentence_test.py
logicalinduction-0.1.6.dist-info/LICENSE
logicalinduction-0.1.6.dist-info/METADATA
logicalinduction-0.1.6.dist-info/WHEEL
logicalinduction-0.1.6.dist-info/top_level.txt
logicalinduction-0.1.6.dist-info/RECORD
