Metadata-Version: 2.1
Name: logicalinduction
Version: 0.1.6
Summary: A computable algorithm for quantifying uncertainty
Author-email: Kōshin Alex Flint <koshin@monasticacademy.org>
License: MIT License
Project-URL: Homepage, https://github.com/monasticacademy/logical-induction
Project-URL: Bug Tracker, https://github.com/monasticacademy/logical-induction/issues
Classifier: Programming Language :: Python :: 3
Classifier: License :: OSI Approved :: MIT License
Classifier: Operating System :: OS Independent
Requires-Python: >=3.9
License-File: LICENSE
